django_mutant-0.2.1.dist-info/DESCRIPTION.rst
django_mutant-0.2.1.dist-info/LICENSE.txt
django_mutant-0.2.1.dist-info/METADATA
django_mutant-0.2.1.dist-info/RECORD
django_mutant-0.2.1.dist-info/WHEEL
django_mutant-0.2.1.dist-info/metadata.json
django_mutant-0.2.1.dist-info/top_level.txt
mutant/__init__.py
mutant/apps.py
mutant/compat.py
mutant/forms.py
mutant/hacks.py
mutant/managers.py
mutant/settings.py
mutant/signals.py
mutant/utils.py
mutant/validators.py
mutant/contrib/__init__.py
mutant/contrib/boolean/__init__.py
mutant/contrib/boolean/models.py
mutant/contrib/boolean/migrations/0001_initial.py
mutant/contrib/boolean/migrations/0002_update_field_defs_app_label.py
mutant/contrib/boolean/migrations/__init__.py
mutant/contrib/file/__init__.py
mutant/contrib/file/models.py
mutant/contrib/file/migrations/0001_initial.py
mutant/contrib/file/migrations/0002_update_field_defs_app_label.py
mutant/contrib/file/migrations/__init__.py
mutant/contrib/geo/__init__.py
mutant/contrib/geo/migrations/0001_initial.py
mutant/contrib/geo/migrations/0002_update_field_defs_app_label.py
mutant/contrib/geo/migrations/__init__.py
mutant/contrib/geo/models/__init__.py
mutant/contrib/geo/models/field.py
mutant/contrib/geo/models/model.py
mutant/contrib/numeric/__init__.py
mutant/contrib/numeric/models.py
mutant/contrib/numeric/migrations/0001_initial.py
mutant/contrib/numeric/migrations/0002_update_field_defs_app_label.py
mutant/contrib/numeric/migrations/__init__.py
mutant/contrib/related/__init__.py
mutant/contrib/related/apps.py
mutant/contrib/related/managers.py
mutant/contrib/related/models.py
mutant/contrib/related/management/__init__.py
mutant/contrib/related/migrations/0001_initial.py
mutant/contrib/related/migrations/0002_update_field_defs_app_label.py
mutant/contrib/related/migrations/__init__.py
mutant/contrib/temporal/__init__.py
mutant/contrib/temporal/models.py
mutant/contrib/temporal/locale/fr/LC_MESSAGES/django.mo
mutant/contrib/temporal/locale/fr/LC_MESSAGES/django.po
mutant/contrib/temporal/migrations/0001_initial.py
mutant/contrib/temporal/migrations/0002_update_field_defs_app_label.py
mutant/contrib/temporal/migrations/__init__.py
mutant/contrib/text/__init__.py
mutant/contrib/text/models.py
